Metadata-Version: 2.1
Name: QaraqalpaqAI
Version: 0.1
Summary: Qaraqalpaqsha moduller
Author: QaraqalpaqAI << Diyarbek Oralbaev >>
Author-email: <diyarbekoralbaev@gmail.com>
Keywords: python,Qaraqalapaq,QaraqalpaqAI,Qaraqalpaq AI,Awdarma,Awdarmashi
